compact_json_qt_gui/__init__.py
compact_json_qt_gui/__main__.py
compact_json_qt_gui-0.1.0.dist-info/entry_points.txt
compact_json_qt_gui-0.1.0.dist-info/WHEEL
compact_json_qt_gui-0.1.0.dist-info/METADATA
compact_json_qt_gui-0.1.0.dist-info/RECORD
