Metadata-Version: 2.1
Name: compact-json-qt-gui
Version: 0.1.0
Summary: Qt GUI for JSON formatting with compact-json
License: MIT
Author: Martin Ueding
Author-email: mu@martin-ueding.de
Requires-Python: >=3.10,<3.12
Classifier: License :: OSI Approved :: MIT License
Classifier: Programming Language :: Python :: 3
Classifier: Programming Language :: Python :: 3.10
Requires-Dist: PySide6 (>=6.4.2,<7.0.0)
Requires-Dist: compact-json (>=1.5.0,<2.0.0)
